panonpy/__init__.py
panonpy/file_manager.py
panonpy/panonpy.py
panonpy/report_manager.py
panonpy/visual_comparer.py
panonpy-1.1.0.dist-info/LICENSE
panonpy-1.1.0.dist-info/METADATA
panonpy-1.1.0.dist-info/WHEEL
panonpy-1.1.0.dist-info/RECORD
