Metadata-Version: 2.1
Name: panonpy
Version: 1.1.0
Summary: A simple image comparer
License: Apache v2.0
Author: fachrulch
Author-email: fachrul.fch@gmail.com
Requires-Python: >=3.13,<4.0
Classifier: License :: Other/Proprietary License
Classifier: Programming Language :: Python :: 3
Classifier: Programming Language :: Python :: 3.13
Requires-Dist: pillow (>=11.1.0,<12.0.0)
